{
  "generator-jhipster": {
    "authenticationType": "oauth2",
    "cacheProvider": "hazelcast",
    "serverPort": "8004",
    "serviceDiscoveryType": "eureka",
    "skipUserManagement": true,
    "baseName": "analyticCollectionService",
    "buildTool": "maven",
    "databaseType": "sql",
    "devDatabaseType": "postgresql",
    "enableHibernateCache": true,
    "enableSwaggerCodegen": false,
    "enableTranslation": true,
    "jhiPrefix": "jhi",
    "languages": ["en", "zh-cn", "zh-tw"],
    "messageBroker": false,
    "nativeLanguage": "en",
    "prodDatabaseType": "postgresql",
    "searchEngine": false,
    "skipClient": true,
    "testFrameworks": [],
    "websocket": false,
    "packageName": "online.kehan.connect.analytic.collection",
    "packageFolder": "online/kehan/connect/analytic/collection",
    "applicationType": "microservice",
    "clientPackageManager": "npm",
    "jhipsterVersion": "6.9.0",
    "creationTimestamp": 1590134460075,
    "embeddableLaunchScript": false,
    "entitySuffix": "",
    "dtoSuffix": "DTO",
    "otherModules": [],
    "blueprints": []
  },
  "entities": [
    "Campaign",
    "CampaignFlow",
    "ConnectConfig",
    "ConnectEvent",
    "ConnectIntent",
    "Recipient",
    "Reminder",
    "ConnectState",
    "TemplateFlow"
  ]
}
